{
  "title": "i8042驱动AUX端口检测失败导致HP ProLiant DL160启动时Soft Lockup",
  "kernel_version": "3.8.0-32-generic (受影响版本至少至 3.8.13.10)",
  "phenomenon": "- 系统启动时 dmesg 报错：\"i8042: Failed to disable AUX port, but continuing anyway... Is this a SiS?\"\n- 随后触发内核 soft lockup，日志显示 \"BUG: soft lockup - CPU#0 stuck for 23s!\"，涉及 CPU 0/2/3/4/5 等多个核心。\n- 堆栈信息显示进程卡在 `stop_machine_cpu_stop`。",
  "root_cause": "i8042 驱动在 HP ProLiant DL160 G5 服务器上尝试操作 AUX 端口（PS/2 鼠标接口）时失败，导致内核在 stop machine 机制中长时间等待，引发 soft lockup。",
  "solution": "根据日志提示，若 AUX 端口实际不存在，可在内核启动参数中添加 `i8042.noaux` 选项规避此问题。",
  "category": "kernel",
  "source_file": "i8042驱动AUX端口检测失败导致HP ProLiant DL160启动时Soft Lockup.txt",
  "content": "内核版本：3.8.0-32-generic (受影响版本至少至 3.8.13.10)\n\n## 问题现象\n- 系统启动时 dmesg 报错：\"i8042: Failed to disable AUX port, but continuing anyway... Is this a SiS?\"\n- 随后触发内核 soft lockup，日志显示 \"BUG: soft lockup - CPU#0 stuck for 23s!\"，涉及 CPU 0/2/3/4/5 等多个核心。\n- 堆栈信息显示进程卡在 `stop_machine_cpu_stop`。\n\n## 问题根因\ni8042 驱动在 HP ProLiant DL160 G5 服务器上尝试操作 AUX 端口（PS/2 鼠标接口）时失败，导致内核在 stop machine 机制中长时间等待，引发 soft lockup。\n\n## 解决方案\n根据日志提示，若 AUX 端口实际不存在，可在内核启动参数中添加 `i8042.noaux` 选项规避此问题。"
}
