{
  "title": "USBIP映射DigitalPersona指纹阅读器时触发Kernel BUG导致应用挂起",
  "kernel_version": "4.14",
  "phenomenon": "- 客户端通过 usbip attach 连接远程 DigitalPersona 指纹阅读器后，内核日志出现 \"vhci_hcd: vhci_device speed not set\" 异常信息。\n- 运行 fprint_demo 使用设备时，程序发生挂起。\n- 系统记录 kernel BUG。",
  "root_cause": "未明确。用户反馈该环境在内核 4.10 版本下正常工作，推测为 4.10 至 4.14 之间的内核变更引入的回归问题。",
  "solution": "暂无。维护者建议将问题发送至 linux-usb@vger.kernel.org 邮件列表进行跟踪处理。",
  "category": "kernel",
  "source_file": "USBIP映射DigitalPersona指纹阅读器时触发Kernel BUG导致应用挂起.txt",
  "content": "内核版本：4.14\n\n## 问题现象\n- 客户端通过 usbip attach 连接远程 DigitalPersona 指纹阅读器后，内核日志出现 \"vhci_hcd: vhci_device speed not set\" 异常信息。\n- 运行 fprint_demo 使用设备时，程序发生挂起。\n- 系统记录 kernel BUG。\n\n## 问题根因\n未明确。用户反馈该环境在内核 4.10 版本下正常工作，推测为 4.10 至 4.14 之间的内核变更引入的回归问题。\n\n## 解决方案\n暂无。维护者建议将问题发送至 linux-usb@vger.kernel.org 邮件列表进行跟踪处理。"
}
