{
  "title": "并发写入RAID1磁盘触发RCU警告及ATA总线错误导致系统挂起",
  "kernel_version": "4.15.5",
  "phenomenon": "- 在向 LUKS 加密的 RAID1 磁盘并发写入多个大文件时触发故障。\n- 4.15.5 版本：内核打印 WARNING `rcu_process_callbacks+0x325/0x360`，随后系统完全挂起，硬盘指示灯常亮，需强制重启。\n- 4.15.0 版本：内核报 `ata3.00: exception Emask 0x10 SAct 0x7ffff87f SErr 0x400100`，显示 `interface fatal error` 及 `SError: { UnrecovData Handshk }`，大量 `WRITE FPDMA QUEUED` 命令失败，系统在链路重置后恢复。\n- 该问题为 4.11.8 版本上的回归问题。",
  "root_cause": "未明确（日志显示 RCU 回调处理异常及 SATA 链路层握手失败，具体代码缺陷未在报告中说明）。",
  "solution": "暂无（报告中标记为 Bug 198861 的重复案例，未提供具体修复补丁）。",
  "category": "kernel",
  "source_file": "并发写入RAID1磁盘触发RCU警告及ATA总线错误导致系统挂起.txt",
  "content": "内核版本：4.15.5\n\n## 问题现象\n- 在向 LUKS 加密的 RAID1 磁盘并发写入多个大文件时触发故障。\n- 4.15.5 版本：内核打印 WARNING `rcu_process_callbacks+0x325/0x360`，随后系统完全挂起，硬盘指示灯常亮，需强制重启。\n- 4.15.0 版本：内核报 `ata3.00: exception Emask 0x10 SAct 0x7ffff87f SErr 0x400100`，显示 `interface fatal error` 及 `SError: { UnrecovData Handshk }`，大量 `WRITE FPDMA QUEUED` 命令失败，系统在链路重置后恢复。\n- 该问题为 4.11.8 版本上的回归问题。\n\n## 问题根因\n未明确（日志显示 RCU 回调处理异常及 SATA 链路层握手失败，具体代码缺陷未在报告中说明）。\n\n## 解决方案\n暂无（报告中标记为 Bug 198861 的重复案例，未提供具体修复补丁）。"
}
